pdf2md/__init__.py
pdf2md/converter.py
pdf2md_dev_lrivera-1.0.0.dist-info/LICENSE
pdf2md_dev_lrivera-1.0.0.dist-info/METADATA
pdf2md_dev_lrivera-1.0.0.dist-info/WHEEL
pdf2md_dev_lrivera-1.0.0.dist-info/top_level.txt
pdf2md_dev_lrivera-1.0.0.dist-info/RECORD
