Metadata-Version: 2.2
Name: pdf2md_dev_lrivera
Version: 1.0.0
Summary: Convierte archivos PDF a formato Markdown extrayendo texto, tablas e imágenes.
Author-email: Leandro Rivera Ríos <leo.232rivera@gmail.com>
Project-URL: Homepage, https://github.com/LeoR22/pdf2md
Classifier: Programming Language :: Python :: 3
Classifier: License :: OSI Approved :: MIT License
Classifier: Operating System :: OS Independent
Requires-Python: >=3.6
License-File: LICENSE
Requires-Dist: pdfplumber
Requires-Dist: Pillow
